popa/__init__.py
popa/big_ass.py
popa/bitch_ass.py
popa/closed_ass.py
popa/dumb_ass.py
popa/fuck.py
popa/normal_ass.py
popa/rich_ass.py
popa/six_seven.py
popa/smart_ass.py
popa/sybau.py
popa/tight_ass.py
popa-0.0.4.dist-info/licenses/LICENSE
popa-0.0.4.dist-info/METADATA
popa-0.0.4.dist-info/WHEEL
popa-0.0.4.dist-info/top_level.txt
popa-0.0.4.dist-info/RECORD
