Metadata-Version: 2.4
Name: POPA
Version: 0.0.4
Summary: POPA MODULE
Author: EGOR
Requires-Python:  >= 3.6
License-File: LICENSE
Dynamic: author
Dynamic: description
Dynamic: description-content-type
Dynamic: license-file
Dynamic: requires-python
Dynamic: summary
